devlib/__init__.py
devlib/util_file.py
bamboxo2go_devlib-0.1.0.dist-info/METADATA
bamboxo2go_devlib-0.1.0.dist-info/WHEEL
bamboxo2go_devlib-0.1.0.dist-info/top_level.txt
bamboxo2go_devlib-0.1.0.dist-info/RECORD
